linkedin2md/__init__.py
linkedin2md/__main__.py
linkedin2md/cli.py
linkedin2md/converter.py
linkedin2md/extractor.py
linkedin2md/formatter.py
linkedin2md/language.py
linkedin2md/parser.py
linkedin2md/protocols.py
linkedin2md/registry.py
linkedin2md/writer.py
linkedin2md/formatters/__init__.py
linkedin2md/formatters/activity.py
linkedin2md/formatters/advertising.py
linkedin2md/formatters/base.py
linkedin2md/formatters/content.py
linkedin2md/formatters/identity.py
linkedin2md/formatters/jobs.py
linkedin2md/formatters/learning.py
linkedin2md/formatters/network.py
linkedin2md/formatters/payments.py
linkedin2md/formatters/professional.py
linkedin2md/formatters/profile.py
linkedin2md/formatters/recommendations.py
linkedin2md/formatters/services.py
linkedin2md/parsers/__init__.py
linkedin2md/parsers/activity.py
linkedin2md/parsers/advertising.py
linkedin2md/parsers/base.py
linkedin2md/parsers/content.py
linkedin2md/parsers/identity.py
linkedin2md/parsers/jobs.py
linkedin2md/parsers/learning.py
linkedin2md/parsers/network.py
linkedin2md/parsers/payments.py
linkedin2md/parsers/professional.py
linkedin2md/parsers/profile.py
linkedin2md/parsers/recommendations.py
linkedin2md/parsers/services.py
linkedin2md-0.3.0.dist-info/METADATA
linkedin2md-0.3.0.dist-info/WHEEL
linkedin2md-0.3.0.dist-info/entry_points.txt
linkedin2md-0.3.0.dist-info/licenses/LICENSE
linkedin2md-0.3.0.dist-info/RECORD
