Metadata-Version: 2.4
Name: linkedin2md
Version: 0.3.0
Summary: Convert LinkedIn data exports to Markdown
Project-URL: Homepage, https://github.com/juanmanueldaza/linkedin2md
Project-URL: Repository, https://github.com/juanmanueldaza/linkedin2md
Project-URL: Issues, https://github.com/juanmanueldaza/linkedin2md/issues
Author-email: Juan Manuel Daza <juanmanueldaza@gmail.com>
License: GPL-2.0
License-File: LICENSE
Keywords: cv,export,linkedin,markdown,parser,resume
Classifier: Development Status :: 4 - Beta
Classifier: Environment :: Console
Classifier: Intended Audience :: Developers
Classifier: Intended Audience :: End Users/Desktop
Classifier: License :: OSI Approved :: GNU General Public License v2 (GPLv2)
Classifier: Operating System :: OS Independent
Classifier: Programming Language :: Python :: 3
Classifier: Programming Language :: Python :: 3.13
Classifier: Programming Language :: Python :: 3.14
Classifier: Topic :: Text Processing :: Markup :: Markdown
Classifier: Topic :: Utilities
Requires-Python: >=3.13
Provides-Extra: dev
Requires-Dist: pyright>=1.1.408; extra == 'dev'
Requires-Dist: pytest>=9.0; extra == 'dev'
Requires-Dist: ruff>=0.9; extra == 'dev'
